{
  "home": {
    "title": "Home",
    "entities": [
      {
        "id": "xyz",
        "type": "section",
        "title": "Section 1",
        "entities": [
          {
            "id": "789",
            "type": "chart",
            "title": "Entity 1",
            "yAxes": []
          }
        ]
      }
    ]
  },
  "pageGroups": [
    {
      "id": "123",
      "url": "group1",
      "title": "Group 1",
      "pages": [
        {
          "id": "abc",
          "url": "page1",
          "title": "Page 1",
          "entities": [
            {
              "id": "789",
              "type": "section",
              "title": "Section 1",
              "entities": [
                {
                  "id": "123",
                  "type": "chart",
                  "title": "Entity 1",
                  "yAxes": []
                },
                {
                  "id": "456",
                  "type": "map",
                  "title": "Entity 2"
                }
              ]
            }
          ]
        },
        {
          "id": "def",
          "url": "page2",
          "title": "Page 2",
          "entities": [
            {
              "id": "789",
              "type": "section",
              "title": "Section 1",
              "entities": [
                {
                  "id": "123",
                  "type": "chart",
                  "title": "Entity 2",
                  "yAxes": []
                }
              ]
            }
          ]
        }
      ]
    },
    {
      "id": "456",
      "url": "group2",
      "title": "Group 2",
      "pages": [
        {
          "id": "abc",
          "url": "page1",
          "title": "Page 1",
          "entities": [
            {
              "id": "789",
              "type": "section",
              "title": "Section 1",
              "entities": [
                {
                  "id": "123",
                  "type": "chart",
                  "title": "Entity 1",
                  "yAxes": []
                }
              ]
            }
          ]
        },
        {
          "id": "def",
          "url": "page2",
          "title": "Page 2",
          "entities": [
            {
              "id": "789",
              "type": "section",
              "title": "Section 1",
              "entities": [
                {
                  "id": "123",
                  "type": "chart",
                  "title": "Entity 1",
                  "yAxes": []
                }
              ]
            }
          ]
        }
      ]
    }
  ]
}
